faytheclient/__init__.py
faytheclient/client.py
faytheclient/exceptions.py
faytheclient/http.py
faytheclient/utils.py
faytheclient-0.0.3.dist-info/AUTHORS
faytheclient-0.0.3.dist-info/LICENSE
faytheclient-0.0.3.dist-info/METADATA
faytheclient-0.0.3.dist-info/WHEEL
faytheclient-0.0.3.dist-info/pbr.json
faytheclient-0.0.3.dist-info/top_level.txt
faytheclient-0.0.3.dist-info/RECORD
